dataflow_custom_extension/__init__.py
dataflow_custom_extension/_version.py
dataflow_custom_extension-0.1.21.data/data/share/jupyter/labextensions/dataflow-custom-extension/package.json
dataflow_custom_extension-0.1.21.data/data/share/jupyter/labextensions/dataflow-custom-extension/static/509.bdb5bad60ed5866a94c0.js
dataflow_custom_extension-0.1.21.data/data/share/jupyter/labextensions/dataflow-custom-extension/static/728.1bf1d18bc7b07996342b.js
dataflow_custom_extension-0.1.21.data/data/share/jupyter/labextensions/dataflow-custom-extension/static/remoteEntry.827e6396281a58c7aebc.js
dataflow_custom_extension-0.1.21.data/data/share/jupyter/labextensions/dataflow-custom-extension/static/style.js
dataflow_custom_extension-0.1.21.data/data/share/jupyter/labextensions/dataflow-custom-extension/static/third-party-licenses.json
dataflow_custom_extension-0.1.21.data/data/share/jupyter/labextensions/dataflow-custom-extension/install.json
dataflow_custom_extension-0.1.21.dist-info/METADATA
dataflow_custom_extension-0.1.21.dist-info/WHEEL
dataflow_custom_extension-0.1.21.dist-info/RECORD
